README.rst
setup.py
xylem.py
xylem.egg-info/PKG-INFO
xylem.egg-info/SOURCES.txt
xylem.egg-info/dependency_links.txt
xylem.egg-info/top_level.txt