Metadata-Version: 1.2
Name: xylem
Version: 0.9.1
Summary: Convert Python Abstract Syntax Trees to readable source code
Home-page: https://github.com/arantonitis/xylem
Author: Ariel Antonitis
Author-email: arant@mit.edu
License: MIT
Platform: UNKNOWN
Classifier: License :: OSI Approved :: MIT License
Classifier: Development Status :: 4 - Beta
Classifier: Intended Audience :: Developers
Classifier: Topic :: Software Development :: Code Generators
Classifier: Programming Language :: Python :: 3.4
Classifier: Programming Language :: Python :: 3.5
Classifier: Programming Language :: Python :: 3.6
Classifier: Programming Language :: Python :: 3.7
Requires-Python: >=3.4
